{
  "sections": {
    "45acf90c-464d-4eba-8131-a969a634bfe5": {
      "type": "image-banner",
      "settings": {
        "image": "shopify:\/\/shop_images\/product_banner.png",
        "image_overlay_opacity": 0,
        "image_height": "small",
        "desktop_content_position": "top-center",
        "show_text_box": false,
        "desktop_content_alignment": "center",
        "color_scheme": "background-1",
        "image_behavior": "none",
        "mobile_content_alignment": "center",
        "stack_images_on_mobile": true,
        "show_text_below": false
      }
    },
    "474b59ac-de28-432c-903d-f6b6cfdf4332": {
      "type": "custom-liquid",
      "settings": {
        "custom_liquid": "{% render 'breadcrumbs' %}",
        "color_scheme": "background-1",
        "padding_top": 16,
        "padding_bottom": 16
      }
    },
    "main": {
      "type": "main-product",
      "blocks": {
        "vendor": {
          "type": "text",
          "settings": {
            "text": "{{ product.vendor }}",
            "text_style": "uppercase"
          }
        },
        "title": {
          "type": "title",
          "settings": {
          }
        },
        "price": {
          "type": "price",
          "settings": {
          }
        },
        "variant_picker": {
          "type": "variant_picker",
          "settings": {
            "picker_type": "button"
          }
        },
        "quantity_selector": {
          "type": "quantity_selector",
          "settings": {
          }
        },
        "description": {
          "type": "description",
          "settings": {
          }
        },
        "share": {
          "type": "share",
          "settings": {
            "share_label": "Share"
          }
        }
      },
      "block_order": [
        "vendor",
        "title",
        "price",
        "variant_picker",
        "quantity_selector",
        "description",
        "share"
      ],
      "settings": {
        "enable_sticky_info": true,
        "media_size": "large",
        "constrain_to_viewport": true,
        "media_fit": "cover",
        "gallery_layout": "thumbnail",
        "media_position": "left",
        "image_zoom": "lightbox",
        "mobile_thumbnails": "hide",
        "hide_variants": true,
        "enable_video_looping": false,
        "padding_top": 36,
        "padding_bottom": 12
      }
    },
    "related-products": {
      "type": "related-products",
      "settings": {
        "heading": "You may also like",
        "heading_size": "h2",
        "products_to_show": 4,
        "columns_desktop": 4,
        "color_scheme": "background-1",
        "image_ratio": "square",
        "show_secondary_image": true,
        "show_vendor": false,
        "show_rating": false,
        "columns_mobile": "2",
        "padding_top": 36,
        "padding_bottom": 28
      }
    },
    "78e8f378-5871-4c5b-a590-e8b04274fdcb": {
      "type": "image-with-text",
      "blocks": {
        "template--18491920285984__78e8f378-5871-4c5b-a590-e8b04274fdcb-16863933499a4abd4a-0": {
          "type": "heading",
          "settings": {
            "heading": "Gift Cards",
            "heading_size": "h1"
          }
        },
        "template--18491920285984__78e8f378-5871-4c5b-a590-e8b04274fdcb-16863933499a4abd4a-1": {
          "type": "text",
          "settings": {
            "text": "<p>The perfect gift for you and your love!<\/p>",
            "text_style": "subtitle"
          }
        }
      },
      "block_order": [
        "template--18491920285984__78e8f378-5871-4c5b-a590-e8b04274fdcb-16863933499a4abd4a-0",
        "template--18491920285984__78e8f378-5871-4c5b-a590-e8b04274fdcb-16863933499a4abd4a-1"
      ],
      "settings": {
        "image": "shopify:\/\/shop_images\/giftcard_d863df8e-2dc9-4e1b-8306-6082131d7cb9.png",
        "height": "adapt",
        "desktop_image_width": "medium",
        "layout": "image_first",
        "desktop_content_position": "middle",
        "desktop_content_alignment": "center",
        "content_layout": "no-overlap",
        "color_scheme": "background-1",
        "image_behavior": "none",
        "mobile_content_alignment": "left",
        "padding_top": 36,
        "padding_bottom": 36
      }
    }
  },
  "order": [
    "45acf90c-464d-4eba-8131-a969a634bfe5",
    "474b59ac-de28-432c-903d-f6b6cfdf4332",
    "main",
    "related-products",
    "78e8f378-5871-4c5b-a590-e8b04274fdcb"
  ]
}